gapi/__main__.py
gapi/read_sheet/__init__.py
gapi/readsheet/__init__.py
gapi/utils/__init__.py
gspi/__main__.py
gspi/read_sheet/__init__.py
gspi/utils/__init__.py
gspi-1.0.3.dist-info/LICENSE
gspi-1.0.3.dist-info/METADATA
gspi-1.0.3.dist-info/WHEEL
gspi-1.0.3.dist-info/entry_points.txt
gspi-1.0.3.dist-info/top_level.txt
gspi-1.0.3.dist-info/RECORD
